Metadata-Version: 1.1
Name: mongotor-skd
Version: 0.1.0
Summary: (MongoDB + Tornado) is an asynchronous driver and toolkit for working with MongoDB inside a Tornado app
Home-page: http://marcelnicolay.github.com/mongotor/
Author: Marcel Nicolay
Author-email: marcel.nicolay@gmail.com
License: OSI
Keywords: mongo,tornado
Platform: UNKNOWN
Classifier: Development Status :: 4 - Beta
Classifier: Intended Audience :: Developers
Classifier: License :: OSI Approved
Classifier: Natural Language :: English
Classifier: Natural Language :: Portuguese (Brazilian)
Classifier: Operating System :: POSIX :: Linux
Classifier: Programming Language :: Python :: 2.7
Classifier: Topic :: Software Development :: Libraries :: Application Frameworks
